personal_lib/__init__.py
personal_lib/utils/__init__.py
personal_lib/utils/common_utils.py
personal_lib/utils/db_utils.py
personal_lib/utils/mail_utils.py
personal_lib/utils/sqlite_config_utils.py
personal_lib/utils/ssh_utils.py
personal_lib/utils/wx_utils.py
personal_lib-1.0.14.dist-info/METADATA
personal_lib-1.0.14.dist-info/WHEEL
personal_lib-1.0.14.dist-info/top_level.txt
personal_lib-1.0.14.dist-info/RECORD
