Metadata-Version: 2.1
Name: personal-lib
Version: 1.0.14
Summary: a personal lib for myself
Home-page: 
Author: zhenggan
Author-email: forzg@qq.com
Requires-Dist: pandas (>=1.1.4)
Requires-Dist: paramiko (>=2.7.2)
Requires-Dist: pymysql (>=1.0.2)
Requires-Dist: requests
Requires-Dist: yagmail (>=0.14.261)
Requires-Dist: dbutils
